aishell/aishell_help.py
aishell/get_screen.py
aishell/main.py
aishell/print.py
aishell/terminal_parser.py
aishell_tools-0.1.0.dist-info/LICENSE
aishell_tools-0.1.0.dist-info/METADATA
aishell_tools-0.1.0.dist-info/WHEEL
aishell_tools-0.1.0.dist-info/entry_points.txt
aishell_tools-0.1.0.dist-info/top_level.txt
aishell_tools-0.1.0.dist-info/RECORD
