Metadata-Version: 2.1
Name: aishell-tools
Version: 0.1.0
Summary: A shell wrapper for building context-aware tools
Author-email: Jonathan Chang <31893406+cccntu@users.noreply.github.com>
Project-URL: Homepage, https://github.com/cccntu/aishell
Classifier: Programming Language :: Python :: 3
Classifier: Programming Language :: Python :: 3.8
Classifier: Programming Language :: Python :: 3.9
Classifier: Programming Language :: Python :: 3.10
Classifier: Programming Language :: Python :: 3.11
Classifier: Programming Language :: Python :: 3.12
Classifier: License :: OSI Approved :: MIT License
Classifier: Operating System :: OS Independent
Requires-Python: >=3.8
License-File: LICENSE
